linkcheck_gui/__init__.py
linkcheck_gui/__main__.py
linkcheck_gui/_release.py
linkcheck_gui/checker.py
linkcheck_gui/configuration.py
linkcheck_gui/contextmenu.py
linkcheck_gui/debug.py
linkcheck_gui/editor.py
linkcheck_gui/editor_qsci.py
linkcheck_gui/editor_qt.py
linkcheck_gui/help.py
linkcheck_gui/lineedit.py
linkcheck_gui/linkchecker_ui_debug.py
linkcheck_gui/linkchecker_ui_editor.py
linkcheck_gui/linkchecker_ui_main.py
linkcheck_gui/linkchecker_ui_options.py
linkcheck_gui/logger.py
linkcheck_gui/options.py
linkcheck_gui/projects.py
linkcheck_gui/properties.py
linkcheck_gui/recentdocs.py
linkcheck_gui/settings.py
linkcheck_gui/statistics.py
linkcheck_gui/syntax.py
linkcheck_gui/urlmodel.py
linkcheck_gui/urlsave.py
linkcheck_gui/validator.py
linkcheck_gui/data/help/lccollection.qhc
linkcheck_gui/data/help/lcdoc.qch
linkcheck_gui/data/rc/linkchecker.rcc
linkcheck_gui/library/__init__.py
linkcheck_gui/library/fileutil.py
linkcheck_gui/library/internal_error.py
linkcheck_gui/library/url.py
linkcheck_gui/library/bookmarks/__init__.py
linkcheck_gui/library/bookmarks/chrome.py
linkcheck_gui/library/bookmarks/chromium.py
linkcheck_gui/library/bookmarks/firefox.py
linkcheck_gui/library/bookmarks/opera.py
linkcheck_gui/library/bookmarks/safari.py
linkcheck_gui/library/bookmarks/winutil.py
linkchecker_gui-10.0.0b4.data/data/share/applications/linkchecker-gui.desktop
linkchecker_gui-10.0.0b4.data/data/share/man/man1/linkchecker-gui.1
linkchecker_gui-10.0.0b4.data/data/share/man/de/man1/linkchecker-gui.1
linkchecker_gui-10.0.0b4.data/data/share/icons/hicolor/128x128/apps/linkchecker-gui.png
linkchecker_gui-10.0.0b4.data/data/share/icons/hicolor/16x16/apps/linkchecker-gui.png
linkchecker_gui-10.0.0b4.data/data/share/icons/hicolor/32x32/apps/linkchecker-gui.png
linkchecker_gui-10.0.0b4.data/data/share/icons/hicolor/48x48/apps/linkchecker-gui.png
linkchecker_gui-10.0.0b4.data/data/share/icons/hicolor/64x64/apps/linkchecker-gui.png
linkchecker_gui-10.0.0b4.dist-info/METADATA
linkchecker_gui-10.0.0b4.dist-info/WHEEL
linkchecker_gui-10.0.0b4.dist-info/entry_points.txt
linkchecker_gui-10.0.0b4.dist-info/licenses/LICENSE
linkchecker_gui-10.0.0b4.dist-info/RECORD
