Metadata-Version: 2.4
Name: LinkChecker-GUI
Version: 10.0.0b4
Summary: GUI for LinkChecker
Project-URL: Homepage, https://github.com/linkchecker/linkchecker-gui
Author: LinkChecker Authors
Maintainer: LinkChecker Authors
License-Expression: GPL-3.0-or-later
License-File: LICENSE
Classifier: Development Status :: 4 - Beta
Classifier: Programming Language :: Python
Classifier: Programming Language :: Python :: 3.9
Classifier: Programming Language :: Python :: 3.10
Classifier: Programming Language :: Python :: 3.11
Classifier: Programming Language :: Python :: 3.12
Classifier: Programming Language :: Python :: 3.13
Classifier: Programming Language :: Python :: 3.14
Classifier: Topic :: Internet :: WWW/HTTP :: Site Management :: Link Checking
Requires-Python: >=3.9
Requires-Dist: linkchecker>=10.1
Requires-Dist: pyqt6
Requires-Dist: pyqt6-qscintilla
